{"title":"Pokemon.Kyurem.Vs.The.Sword.Of.Justice.2013.DVDRip.XviD-ViP3R","uid":8364113,"size":744521810,"categoryP":"video","categoryS":"movies","magnet":"?xt=urn:btih:0ab25908726789e72ee1c0edc972ec3adb49efd6&amp;dn=Pokemon.Kyurem.Vs.The.Sword.Of.Justice.2013.DVDRip.XviD-ViP3R&amp;tr=udp%3A%2F%2Ftracker.openbittorrent.com%3A80&amp;tr=udp%3A%2F%2Fopen.demonii.com%3A1337&amp;tr=udp%3A%2F%2Ftracker.coppersurfer.tk%3A6969&amp;tr=udp%3A%2F%2Fexodus.desync.com%3A6969","seeders":1,"leechers":0,"uploader":"sceneline","files":7,"time":1365719643,"description":"-\n &lt;a href=&quot;\nhttp://www.Speed.&quot; rel=&quot;nofollow&quot; target=&quot;_NEW&quot;&gt;\nhttp://www.Speed.&lt;/a&gt; Cd       the fast  and The Hottest Private Tracker on the net &lt;a href=&quot;\nhttp://www.Speed.&quot; rel=&quot;nofollow&quot; target=&quot;_NEW&quot;&gt;\nhttp://www.Speed.&lt;/a&gt; Cd\n\nPlease Seed back to make the speed Faster!!\n ............ NFO .............\n-\n &lt;a href=&quot;\nhttp://www.Speed.&quot; rel=&quot;nofollow&quot; target=&quot;_NEW&quot;&gt;\nhttp://www.Speed.&lt;/a&gt; Cd\n          @@@  @@@  @@@  @@@@@@@   @@@@@@   @@@@@@@\n          @@@  @@@  @@@  @@@@@@@@  @@@@@@@  @@@@@@@@\n          @@!  @@@  @@!  @@!  @@@      @@@  @@!  @@@\n          !@!  @!@  !@!  !@!  @!@      @!@  !@!  @!@\n          @!@  !@!  !!@  @!@@!@!   @!@!!@   @!@!!@!\n          !@!  !!!  !!!  !!@!!!    !!@!@!   !!@!@!\n          :!:  !!:  !!:  !!:           !!:  !!: :!!\n           ::!!:!   :!:  :!:           :!:  :!:  !:!\n            ::::     ::   ::       :: ::::  ::   :::\n             :       :     :         : : :    :  : :\n  Pokemon.Kyurem.Vs.The.Sword.Of.Justice.2013.DVDRip.XviD-ViP3R\n\n FILE INFO \n\n\n TiTLE.........[ Pokemon The Movie Kyurem Vs The Sword Of Justice\n AUDiO.........[ 48000Hz  128 kb/s\n LANGUAGE......[ English\n ViDEO.........[ 1243 kbps XviD 23.976 FPS\n RESOLUTiON....[ 656 x 368\n ASPECT RATiO..[ 1.783\n SUBS..........[ English\n FiLES.........[ 1\n SiZE..........[ 700 MB\n RUNTIME.......[ 1:11:17\n GENRE.........[ Animation | Adventure \n RARS..........[ Never\n\n\n MOVIE INFO \n\n\n IMDB: N/A\n MORE iNFO:\n DIRECTOR: Kunihiko Yuyama, Hideki Sonoda\n CAST: Sarah Natochenny, Ikue Ohtani, Eileen Stevens, \n       Jason Griffith, Vic Mignogna            \n \n PLOT:\n Ash and Pikachu along with their friends Iris and Cilan are on a \n train headed to the next stop on their journey. From the train \n Ash spots an injured Pokemon one he's never seen before. He's \n trying to figure out how he can help when the train is attacked \n by the Legendary Kyurem a Dragon-type Pokemon with immense power! \n Ash and the others barely manage to escape the rampaging Kyurem's \n attack and as the dust settles they turn their attention to the \n injured Pokemon. Their new acquaintance turns out to be the \n Mythical Pokemon Keldeo and it's on a mission to rescue its \n friends Cobalion Terrakion and Virizion the Legendary Pokemon \n known as the Swords of Justice from Kyurem's icy clutches! But \n Kyurem's rampage isn't over and it's drawing power from Reshiram \n and Zekrom changing into Black Kyurem or White Kyurem to make its \n attacks even stronger! Why is Kyurem attacking Ash and his \n friends with such unrelenting fury? How will they be able to \n overcome this danger? To protect its friends to discover true \n power and genuine courage and to preserve its bond with Ash and \n its companions a hidden strength awakens within Keldeo \n\n\n NOTES \n\n                         \n *Greets*\n BHRG, INFERNO, westdenco, greenbud1969, eXceSs, S4A, m2g\n\n Beware Of Fakers, Only Download From Trusted Sources.","torrent":{"xt":"urn:btih:0ab25908726789e72ee1c0edc972ec3adb49efd6","amp;dn":"Pokemon.Kyurem.Vs.The.Sword.Of.Justice.2013.DVDRip.XviD-ViP3R","amp;tr":["udp%3A%2F%2Ftracker.openbittorrent.com%3A80","udp%3A%2F%2Fopen.demonii.com%3A1337","udp%3A%2F%2Ftracker.coppersurfer.tk%3A6969","udp%3A%2F%2Fexodus.desync.com%3A6969"],"infoHash":"0ab25908726789e72ee1c0edc972ec3adb49efd6","infoHashBuffer":{"type":"Buffer","data":[10,178,89,8,114,103,137,231,46,225,192,237,201,114,236,58,219,73,239,214]},"announce":[],"urlList":[]}}