{"title":"UFC 167: Official Weigh-In 720p [P2PDL]","uid":9200722,"size":709584436,"categoryP":"video","categoryS":"hd___tv_shows","magnet":"?xt=urn:btih:1054fb442ee408d82320f973e4bd96640aa9ae4d&amp;dn=UFC+167%3A+Official+Weigh-In+720p+%5BP2PDL%5D&amp;tr=udp%3A%2F%2Ftracker.openbittorrent.com%3A80&amp;tr=udp%3A%2F%2Fopen.demonii.com%3A1337&amp;tr=udp%3A%2F%2Ftracker.coppersurfer.tk%3A6969&amp;tr=udp%3A%2F%2Fexodus.desync.com%3A6969","seeders":1,"leechers":1,"uploader":"TeX","files":1,"time":1384590472,"description":"Streamed live on Nov 15, 2013\nWatch the official weigh-in for UFC 167, live from the MGM Grand Garden Arena, Friday, November 15th at 7PM/4PM ET/PT.\nSource:","torrent":{"xt":"urn:btih:1054fb442ee408d82320f973e4bd96640aa9ae4d","amp;dn":"UFC+167%3A+Official+Weigh-In+720p+%5BP2PDL%5D","amp;tr":["udp%3A%2F%2Ftracker.openbittorrent.com%3A80","udp%3A%2F%2Fopen.demonii.com%3A1337","udp%3A%2F%2Ftracker.coppersurfer.tk%3A6969","udp%3A%2F%2Fexodus.desync.com%3A6969"],"infoHash":"1054fb442ee408d82320f973e4bd96640aa9ae4d","infoHashBuffer":{"type":"Buffer","data":[16,84,251,68,46,228,8,216,35,32,249,115,228,189,150,100,10,169,174,77]},"announce":[],"urlList":[]}}