{"title":"Katya - Wild Asshole Slut Part III","uid":6587733,"size":223092545,"categoryP":"porn","categoryS":"movie_clips","magnet":"?xt=urn:btih:163038bcf36cce6edeaa8155b761bc7e8e15d773&amp;dn=Katya+-+Wild+Asshole+Slut+Part+III&amp;tr=udp%3A%2F%2Ftracker.openbittorrent.com%3A80&amp;tr=udp%3A%2F%2Fopen.demonii.com%3A1337&amp;tr=udp%3A%2F%2Ftracker.coppersurfer.tk%3A6969&amp;tr=udp%3A%2F%2Fexodus.desync.com%3A6969","seeders":1,"leechers":0,"uploader":"chkm8te","files":1,"time":1312682602,"description":"Screens: &lt;a href=&quot;\nhttp://4ufrom.me/viewer.php?file=xj5ugjeekzoukpecvkw7.jpg&quot; rel=&quot;nofollow&quot; target=&quot;_NEW&quot;&gt;\nhttp://4ufrom.me/viewer.php?file=xj5ugjeekzoukpecvkw7.jpg&lt;/a&gt;","torrent":{"xt":"urn:btih:163038bcf36cce6edeaa8155b761bc7e8e15d773","amp;dn":"Katya+-+Wild+Asshole+Slut+Part+III","amp;tr":["udp%3A%2F%2Ftracker.openbittorrent.com%3A80","udp%3A%2F%2Fopen.demonii.com%3A1337","udp%3A%2F%2Ftracker.coppersurfer.tk%3A6969","udp%3A%2F%2Fexodus.desync.com%3A6969"],"infoHash":"163038bcf36cce6edeaa8155b761bc7e8e15d773","infoHashBuffer":{"type":"Buffer","data":[22,48,56,188,243,108,206,110,222,170,129,85,183,97,188,126,142,21,215,115]},"announce":[],"urlList":[]}}