{"title":"MY SELECTION OF RARITIES FROM THE 70'S PART 14","uid":7998552,"size":57396646,"categoryP":"audio","categoryS":"music","magnet":"?xt=urn:btih:27a6cad8fe5303fa87174d8b0c3f25155d6d04dc&amp;dn=MY+SELECTION+OF+RARITIES+FROM+THE+70%27S+PART+14&amp;tr=udp%3A%2F%2Ftracker.openbittorrent.com%3A80&amp;tr=udp%3A%2F%2Fopen.demonii.com%3A1337&amp;tr=udp%3A%2F%2Ftracker.coppersurfer.tk%3A6969&amp;tr=udp%3A%2F%2Fexodus.desync.com%3A6969","seeders":1,"leechers":1,"uploader":"Lucpenta","files":16,"time":1357685029,"description":"01 I Nomadi - Un Giorno Insieme\n02 Charles Aznavour - After Loving  You\n03 Pussycat - I'll Be Your Woman - Pussycat\n04 Teclado Espetacular - De Tanto Amor(Brasil)\n05 Andy Gibb &amp; Olivia Newton John - Rest Your Love on Me\n06 Pooh - Ninna nanna\n07 Frederic Francois - Je Reve Sur Mon Piano\n08 Dana - All Kinds Of Everything\n09 John Conlee - Friday Night Blues\n10 Blow Up - Rainbow (Brasil)\n11 Peppino Gagliardi - Sempre... Sempre...\n12 Janie Frickie - Tell Me A Lie\n13 Eric Carmen - Never Gonna Fall in Love Again\n14 Romuald - Celui Qui Reste Et Celui Qui S'En Va\n15 Free Sound Orchestra - Love's Whistle(Brasil)\n16 Collage - Donna Musica\n\n\nIf they shut down this site, i will be at: kat ph (kickass torr..)","torrent":{"xt":"urn:btih:27a6cad8fe5303fa87174d8b0c3f25155d6d04dc","amp;dn":"MY+SELECTION+OF+RARITIES+FROM+THE+70%27S+PART+14","amp;tr":["udp%3A%2F%2Ftracker.openbittorrent.com%3A80","udp%3A%2F%2Fopen.demonii.com%3A1337","udp%3A%2F%2Ftracker.coppersurfer.tk%3A6969","udp%3A%2F%2Fexodus.desync.com%3A6969"],"infoHash":"27a6cad8fe5303fa87174d8b0c3f25155d6d04dc","infoHashBuffer":{"type":"Buffer","data":[39,166,202,216,254,83,3,250,135,23,77,139,12,63,37,21,93,109,4,220]},"announce":[],"urlList":[]}}