{"title":"Confessions Of A Coed 3 (3rd Degree) *NEW 2014* WEB-DL SPLIT SCE","uid":11115859,"size":1229886772,"categoryP":"porn","categoryS":"movies","magnet":"?xt=urn:btih:3c8b74a453ddfe7cfb739ab8991d9838fbdb06b4&amp;dn=Confessions+Of+A+Coed+3+%283rd+Degree%29+%2ANEW+2014%2A+WEB-DL+SPLIT+SCE&amp;tr=udp%3A%2F%2Ftracker.openbittorrent.com%3A80&amp;tr=udp%3A%2F%2Fopen.demonii.com%3A1337&amp;tr=udp%3A%2F%2Ftracker.coppersurfer.tk%3A6969&amp;tr=udp%3A%2F%2Fexodus.desync.com%3A6969","seeders":1,"leechers":6,"uploader":"TKTh3K1ng","files":4,"time":1411855877,"description":"Confessions Of A Coed 3 (3rd Degree) **NEW 2014** WEB-DL SPLIT SCENES\n\nCountry : USA\nGenre : All Sex, School Girls, Young (18+) Ladies\nDuration : 1 hour and 53 minutes\nLanguage : English Directed by : Mike Quasar\n\nStudio : Third Degree Films \n\nStarring : Jodi Taylor, Kacy Lane, Ruby Rayes, Tali Dova, Marco Banderas, Will Powers, Mark Wood, Anthony Rosano \n\nDescription : Pull an all-nighter with the hottest co-eds on campus! Their tight little pussies are wet and ready for a good hard schooling and you'll love their enthusiastic blow jobs! They can not wait to get you back to their dorm rooms for some very long and hard study sessions, so do not let them down - give them the hardcore lessons they'll never forget! \n &lt;a href=&quot;\nhttp://imgking.org/?g=765878&quot; rel=&quot;nofollow&quot; target=&quot;_NEW&quot;&gt;\nhttp://imgking.org/?g=765878&lt;/a&gt;","torrent":{"xt":"urn:btih:3c8b74a453ddfe7cfb739ab8991d9838fbdb06b4","amp;dn":"Confessions+Of+A+Coed+3+%283rd+Degree%29+%2ANEW+2014%2A+WEB-DL+SPLIT+SCE","amp;tr":["udp%3A%2F%2Ftracker.openbittorrent.com%3A80","udp%3A%2F%2Fopen.demonii.com%3A1337","udp%3A%2F%2Ftracker.coppersurfer.tk%3A6969","udp%3A%2F%2Fexodus.desync.com%3A6969"],"infoHash":"3c8b74a453ddfe7cfb739ab8991d9838fbdb06b4","infoHashBuffer":{"type":"Buffer","data":[60,139,116,164,83,221,254,124,251,115,154,184,153,29,152,56,251,219,6,180]},"announce":[],"urlList":[]}}