{"title":"Sniper Elite: Nazi Zombie Army + coop (tunngle)","uid":8210005,"size":4317629802,"categoryP":"games","categoryS":"pc","magnet":"?xt=urn:btih:3ed6101185be566d9ac4889dedca068b384d54cc&amp;dn=Sniper+Elite%3A+Nazi+Zombie+Army+%2B+coop+%28tunngle%29&amp;tr=udp%3A%2F%2Ftracker.openbittorrent.com%3A80&amp;tr=udp%3A%2F%2Fopen.demonii.com%3A1337&amp;tr=udp%3A%2F%2Ftracker.coppersurfer.tk%3A6969&amp;tr=udp%3A%2F%2Fexodus.desync.com%3A6969","seeders":1,"leechers":1,"uploader":"gtshame","files":-1,"time":1362220690,"description":"tunngle.net/wiki/Network:Sniper_Elite:_Nazi_Zombie_Army more info\nU CAN PLAY WITHOUT TUNNGLE JUST DOWNLOAD STEAM\n\n HOW TO PLAY\n\n    Install Sniper Elite: Nazi Zombie Army (FLT Release recommended)\n    Download the MP-Fix V2 and extract it to your Game Folder and overwrite\n    Download and Install Steam Client\n    (Optional) Download latest GreenLuma and extract it to your Steam Folder\n    Run &quot;steam.exe&quot; and login to Steam\n    (Optional) Join the Steam Community Group\n    Join the Sniper Elite: Nazi Zombie Army Network\n    Start the Game via Shortcut or &quot;NZA.exe&quot;\n    Go to &quot;Cooperative&quot;\n    Join or Host any Match via Steam Invites\n    Have Fun \n\nHELP SECTION\nHOW TO FIX: CRASHING\n\n    Delete your &quot;bin&quot; Folder and apply the MP-Fix V2 again\n    Run the &quot;NZA.exe&quot; as Administrator\n    Press ALT + Enter, if you have a black screen\n    Delete File binSteam_API.dll \n\nHOW TO FIX: LANGUAGE MISSING\n\n    Download Language Pack and extract it to your game folder \n\nHOW TO: INVITE\n\n    Use the MP-Fix V2and GreenLuma to Invite:\n        Follow the Instructions on the Top\n        Add a Friend or join the Steam Community Group\n        Start Game and host a Game\n        Open Steam Overlay by pressing SHIFT + TAB\n        Press &quot;View all Friends&quot; (left bottom)\n        Go to Friends or Groups Tab\n        Right click on the Player Name\n        Select &quot;Invite to Game&quot; \n\nHOW TO: ADD STEAM FRIENDS\n\n    To unlock Friends Feature in Steam:\n    Buy any Game on Steam or Unlock Friends for GreenLuma\n    Find your Friend's Steam Profile\n    Click on &quot;Add Friend&quot; \n\nADVANCED TUTORIALS\n\n    Guide by FreeTP.Ru (Russian) ","torrent":{"xt":"urn:btih:3ed6101185be566d9ac4889dedca068b384d54cc","amp;dn":"Sniper+Elite%3A+Nazi+Zombie+Army+%2B+coop+%28tunngle%29","amp;tr":["udp%3A%2F%2Ftracker.openbittorrent.com%3A80","udp%3A%2F%2Fopen.demonii.com%3A1337","udp%3A%2F%2Ftracker.coppersurfer.tk%3A6969","udp%3A%2F%2Fexodus.desync.com%3A6969"],"infoHash":"3ed6101185be566d9ac4889dedca068b384d54cc","infoHashBuffer":{"type":"Buffer","data":[62,214,16,17,133,190,86,109,154,196,136,157,237,202,6,139,56,77,84,204]},"announce":[],"urlList":[]}}