{"title":"Tin.Cup.1996.iNTERNAL.DVDRip.XviD-iLLUSiON","uid":8741461,"size":1466851457,"categoryP":"video","categoryS":"movies","magnet":"?xt=urn:btih:4946a36ee6f9ae3d4a99eb90db45f86d35986783&amp;dn=Tin.Cup.1996.iNTERNAL.DVDRip.XviD-iLLUSiON&amp;tr=udp%3A%2F%2Ftracker.openbittorrent.com%3A80&amp;tr=udp%3A%2F%2Fopen.demonii.com%3A1337&amp;tr=udp%3A%2F%2Ftracker.coppersurfer.tk%3A6969&amp;tr=udp%3A%2F%2Fexodus.desync.com%3A6969","seeders":1,"leechers":0,"uploader":"TvTeam","files":7,"time":1374800764,"description":"::::::::::::::::::::::::::::::::::::::::::::::::::::::::::::::::::::::::::\n  &lt;a href=&quot;\nhttp://www.torrenting.com&quot; rel=&quot;nofollow&quot; target=&quot;_NEW&quot;&gt;\nhttp://www.torrenting.com&lt;/a&gt;\n\n::::::::::::::::::::::::::::::::::::::::::::::::::::::::::::::::::::::::::\n\n(((((((((((((= Enjoy No RAR releases =))))))))))))))))))))\n\n\n...................................NFO:....................................\n\nEnjoy our Fast Upload.\nFor more info about this release, open .NFO file with notepad !!!\n\n-------------------------------------------------------------------------------------\n\n\nMust Try:  &lt;a href=&quot; http://www.torrenting.com&quot; rel=&quot;nofollow&quot; target=&quot;_NEW&quot;&gt; http://www.torrenting.com&lt;/a&gt;\n\nVisit it, enjoy. I am sure you'll like it.","torrent":{"xt":"urn:btih:4946a36ee6f9ae3d4a99eb90db45f86d35986783","amp;dn":"Tin.Cup.1996.iNTERNAL.DVDRip.XviD-iLLUSiON","amp;tr":["udp%3A%2F%2Ftracker.openbittorrent.com%3A80","udp%3A%2F%2Fopen.demonii.com%3A1337","udp%3A%2F%2Ftracker.coppersurfer.tk%3A6969","udp%3A%2F%2Fexodus.desync.com%3A6969"],"infoHash":"4946a36ee6f9ae3d4a99eb90db45f86d35986783","infoHashBuffer":{"type":"Buffer","data":[73,70,163,110,230,249,174,61,74,153,235,144,219,69,248,109,53,152,103,131]},"announce":[],"urlList":[]}}