{"title":"HOME REPAIR HAND BOOK-MANTESHWER","uid":5767513,"size":19421352,"categoryP":"other","categoryS":"e_books","magnet":"?xt=urn:btih:50880e5183b9119de6e4cc73d90d9f68a187e83d&amp;dn=HOME+REPAIR+HAND+BOOK-MANTESHWER&amp;tr=udp%3A%2F%2Ftracker.openbittorrent.com%3A80&amp;tr=udp%3A%2F%2Fopen.demonii.com%3A1337&amp;tr=udp%3A%2F%2Ftracker.coppersurfer.tk%3A6969&amp;tr=udp%3A%2F%2Fexodus.desync.com%3A6969","seeders":1,"leechers":0,"uploader":"MANTESH","files":3,"time":1281968455,"description":"\n\n\nSunset Books are known for their great, clear illustrations, plans, and diagrams. This is another\nof their well-organized, extensively illustrated guides to the basics of home repair. Clearly written\nand indexed for easy reference, and covering a large range of home repair problems, inside and out,\nincluding trouble-shooting with appliances and outdoor equipment, this is a good, basic book for anyone\nwho wants to save some money on home repairs by figuring out how to do-it-yourself. You, too, can become \nthe little engine that could, and this book will get you started!....","torrent":{"xt":"urn:btih:50880e5183b9119de6e4cc73d90d9f68a187e83d","amp;dn":"HOME+REPAIR+HAND+BOOK-MANTESHWER","amp;tr":["udp%3A%2F%2Ftracker.openbittorrent.com%3A80","udp%3A%2F%2Fopen.demonii.com%3A1337","udp%3A%2F%2Ftracker.coppersurfer.tk%3A6969","udp%3A%2F%2Fexodus.desync.com%3A6969"],"infoHash":"50880e5183b9119de6e4cc73d90d9f68a187e83d","infoHashBuffer":{"type":"Buffer","data":[80,136,14,81,131,185,17,157,230,228,204,115,217,13,159,104,161,135,232,61]},"announce":[],"urlList":[]}}