{"title":"Hot.In.Cleveland.S05E11.720p.HDTV.x264-KILLERS[rartv]","uid":10388303,"size":517146116,"categoryP":"video","categoryS":"hd___tv_shows","magnet":"?xt=urn:btih:5b5ddc6387c6826cfef811cf53aaa9e43aa9364e&amp;dn=Hot.In.Cleveland.S05E11.720p.HDTV.x264-KILLERS%5Brartv%5D&amp;tr=udp%3A%2F%2Ftracker.openbittorrent.com%3A80&amp;tr=udp%3A%2F%2Fopen.demonii.com%3A1337&amp;tr=udp%3A%2F%2Ftracker.coppersurfer.tk%3A6969&amp;tr=udp%3A%2F%2Fexodus.desync.com%3A6969","seeders":1,"leechers":0,"uploader":"Drarbg","files":3,"time":1403160077,"description":"Hot.In.Cleveland.S05E11.720p.HDTV.x264-KILLERS[rartv]\n-----------------------------------------\nScreens : &lt;a href=&quot;\nhttp://imagecurl.org/viewer.php?file=44595334768383219764.jpg&quot; rel=&quot;nofollow&quot; target=&quot;_NEW&quot;&gt;\nhttp://imagecurl.org/viewer.php?file=44595334768383219764.jpg&lt;/a&gt;\n\n-----------------------------------------\nAuto Media Info :\nVideo Format........: AVC\nCodec ID............: V_MPEG4/ISO/AVC\nLength..............: 20mn29s\nVideo...............: 1280x720 ( 23.976fps )\nBitrate.............: 2913Kbps\nAudio Format........: AC-3\nCodec ID............: A_AC3\nBit rate mode.......: Constant\nBitrate.............: 384Kbps\nChannel(s)..........: 2 channels\n\n","torrent":{"xt":"urn:btih:5b5ddc6387c6826cfef811cf53aaa9e43aa9364e","amp;dn":"Hot.In.Cleveland.S05E11.720p.HDTV.x264-KILLERS%5Brartv%5D","amp;tr":["udp%3A%2F%2Ftracker.openbittorrent.com%3A80","udp%3A%2F%2Fopen.demonii.com%3A1337","udp%3A%2F%2Ftracker.coppersurfer.tk%3A6969","udp%3A%2F%2Fexodus.desync.com%3A6969"],"infoHash":"5b5ddc6387c6826cfef811cf53aaa9e43aa9364e","infoHashBuffer":{"type":"Buffer","data":[91,93,220,99,135,198,130,108,254,248,17,207,83,170,169,228,58,169,54,78]},"announce":[],"urlList":[]}}