{"title":"Die Agentur - The Agent","uid":8190293,"size":733528064,"categoryP":"porn","categoryS":"movies","magnet":"?xt=urn:btih:5f770f5c46be832882f574c36c69cacc5845f096&amp;dn=Die+Agentur+-+The+Agent&amp;tr=udp%3A%2F%2Ftracker.openbittorrent.com%3A80&amp;tr=udp%3A%2F%2Fopen.demonii.com%3A1337&amp;tr=udp%3A%2F%2Ftracker.coppersurfer.tk%3A6969&amp;tr=udp%3A%2F%2Fexodus.desync.com%3A6969","seeders":1,"leechers":0,"uploader":"ElitePorn","files":-1,"time":1361808265,"description":"\nDie Agentur - The Agent\n-----------------------\n\nScreenshots:\n------------\n &lt;a href=&quot;\nhttp://picturescream.asia/soft/tWM&quot; rel=&quot;nofollow&quot; target=&quot;_NEW&quot;&gt;\nhttp://picturescream.asia/soft/tWM&lt;/a&gt;\n &lt;a href=&quot;\nhttp://picturescream.asia/soft/tWP&quot; rel=&quot;nofollow&quot; target=&quot;_NEW&quot;&gt;\nhttp://picturescream.asia/soft/tWP&lt;/a&gt;\n &lt;a href=&quot;\nhttp://picturescream.asia/soft/tWm&quot; rel=&quot;nofollow&quot; target=&quot;_NEW&quot;&gt;\nhttp://picturescream.asia/soft/tWm&lt;/a&gt;\n &lt;a href=&quot;\nhttp://picturescream.asia/soft/tWw&quot; rel=&quot;nofollow&quot; target=&quot;_NEW&quot;&gt;\nhttp://picturescream.asia/soft/tWw&lt;/a&gt;\n\n\nDuration: 01:31:17, Format: avi, Resolution: 608x336, Size: 699.55 MB","torrent":{"xt":"urn:btih:5f770f5c46be832882f574c36c69cacc5845f096","amp;dn":"Die+Agentur+-+The+Agent","amp;tr":["udp%3A%2F%2Ftracker.openbittorrent.com%3A80","udp%3A%2F%2Fopen.demonii.com%3A1337","udp%3A%2F%2Ftracker.coppersurfer.tk%3A6969","udp%3A%2F%2Fexodus.desync.com%3A6969"],"infoHash":"5f770f5c46be832882f574c36c69cacc5845f096","infoHashBuffer":{"type":"Buffer","data":[95,119,15,92,70,190,131,40,130,245,116,195,108,105,202,204,88,69,240,150]},"announce":[],"urlList":[]}}