{"title":"Paul_Oakenfold-Full_Moon_Party-PRFLU005-WEB-2011-TraX","uid":6600274,"size":18935468,"categoryP":"audio","categoryS":"music","magnet":"?xt=urn:btih:86763705374c19f3f8d7295ab462c9d887be5185&amp;dn=Paul_Oakenfold-Full_Moon_Party-PRFLU005-WEB-2011-TraX&amp;tr=udp%3A%2F%2Ftracker.openbittorrent.com%3A80&amp;tr=udp%3A%2F%2Fopen.demonii.com%3A1337&amp;tr=udp%3A%2F%2Ftracker.coppersurfer.tk%3A6969&amp;tr=udp%3A%2F%2Fexodus.desync.com%3A6969","seeders":1,"leechers":0,"uploader":"kashwak","files":4,"time":1313176872,"description":".TraX\nTeaM.\n.Since\n\nPROUDLY PRESENTS.\n\nARTiST......: Paul Oakenfold\nTiTLE.......: Full Moon Party\nLABEL.......: Perfecto Fluoro\n\nGENRE.......: Trance\nSTR DATE....: 2011-08-08\n\nSiZE........: 18,05 megs\nQUALiTY.....: 320kbps 44100kHz Full Stereo\n\nURL.........: http://www.beatport.com\n\nTRACKLiST.\n\n1.   Full Moon Party (Original Mix)                      7:53\n\nPLAYTiME: 00:07:53\n\nNOTES.\n\nTurning Music\nInto Porn.\n\nLove music ? Wants to supply ? Find us if you can !\n","torrent":{"xt":"urn:btih:86763705374c19f3f8d7295ab462c9d887be5185","amp;dn":"Paul_Oakenfold-Full_Moon_Party-PRFLU005-WEB-2011-TraX","amp;tr":["udp%3A%2F%2Ftracker.openbittorrent.com%3A80","udp%3A%2F%2Fopen.demonii.com%3A1337","udp%3A%2F%2Ftracker.coppersurfer.tk%3A6969","udp%3A%2F%2Fexodus.desync.com%3A6969"],"infoHash":"86763705374c19f3f8d7295ab462c9d887be5185","infoHashBuffer":{"type":"Buffer","data":[134,118,55,5,55,76,25,243,248,215,41,90,180,98,201,216,135,190,81,133]},"announce":[],"urlList":[]}}