{"title":"WHAT'S MY LINE ? -- Jack E. Leonard and mystery guest Margaret T","uid":9378903,"size":82468846,"categoryP":"video","categoryS":"tv_shows","magnet":"?xt=urn:btih:8aa0b60fb58c44bb021dc07a3cec2f249f76acc0&amp;dn=WHAT%27S+MY+LINE+%3F+--+Jack+E.+Leonard+and+mystery+guest+Margaret+T&amp;tr=udp%3A%2F%2Ftracker.openbittorrent.com%3A80&amp;tr=udp%3A%2F%2Fopen.demonii.com%3A1337&amp;tr=udp%3A%2F%2Ftracker.coppersurfer.tk%3A6969&amp;tr=udp%3A%2F%2Fexodus.desync.com%3A6969","seeders":1,"leechers":0,"uploader":"TheExecutive","files":-1,"time":1387677471,"description":".","torrent":{"xt":"urn:btih:8aa0b60fb58c44bb021dc07a3cec2f249f76acc0","amp;dn":"WHAT%27S+MY+LINE+%3F+--+Jack+E.+Leonard+and+mystery+guest+Margaret+T","amp;tr":["udp%3A%2F%2Ftracker.openbittorrent.com%3A80","udp%3A%2F%2Fopen.demonii.com%3A1337","udp%3A%2F%2Ftracker.coppersurfer.tk%3A6969","udp%3A%2F%2Fexodus.desync.com%3A6969"],"infoHash":"8aa0b60fb58c44bb021dc07a3cec2f249f76acc0","infoHashBuffer":{"type":"Buffer","data":[138,160,182,15,181,140,68,187,2,29,192,122,60,236,47,36,159,118,172,192]},"announce":[],"urlList":[]}}