{"title":"Teens In Tight Jeans - Lexi Diamond.wmv","uid":7290710,"size":300362531,"categoryP":"porn","categoryS":"movie_clips","magnet":"?xt=urn:btih:8d94321ffcf34ebc9a4bf1d73abd28dcf83696da&amp;dn=Teens+In+Tight+Jeans+-+Lexi+Diamond.wmv&amp;tr=udp%3A%2F%2Ftracker.openbittorrent.com%3A80&amp;tr=udp%3A%2F%2Fopen.demonii.com%3A1337&amp;tr=udp%3A%2F%2Ftracker.coppersurfer.tk%3A6969&amp;tr=udp%3A%2F%2Fexodus.desync.com%3A6969","seeders":1,"leechers":0,"uploader":"1.No.1","files":-1,"time":1337725033,"description":"Teens In Tight Jeans - Lexi Diamond.wmv\n\n2011, All sex, Hardcore, Straight, XXX, Adult\n\n720 x 480\n\n00:23:55\n\n286.45 MB\n\nScreens\n &lt;a href=&quot;\nhttp://www.pixsor.com/share-0A73_4FBBF515.html&quot; rel=&quot;nofollow&quot; target=&quot;_NEW&quot;&gt;\nhttp://www.pixsor.com/share-0A73_4FBBF515.html&lt;/a&gt;\n &lt;a href=&quot;\nhttp://www.pixsor.com/share-8DBA_4FBBF515.html&quot; rel=&quot;nofollow&quot; target=&quot;_NEW&quot;&gt;\nhttp://www.pixsor.com/share-8DBA_4FBBF515.html&lt;/a&gt;\n &lt;a href=&quot;\nhttp://www.pixsor.com/share-9457_4FBBF515.html&quot; rel=&quot;nofollow&quot; target=&quot;_NEW&quot;&gt;\nhttp://www.pixsor.com/share-9457_4FBBF515.html&lt;/a&gt;\n &lt;a href=&quot;\nhttp://www.pixsor.com/share-6DCD_4FBBF515.html&quot; rel=&quot;nofollow&quot; target=&quot;_NEW&quot;&gt;\nhttp://www.pixsor.com/share-6DCD_4FBBF515.html&lt;/a&gt;","torrent":{"xt":"urn:btih:8d94321ffcf34ebc9a4bf1d73abd28dcf83696da","amp;dn":"Teens+In+Tight+Jeans+-+Lexi+Diamond.wmv","amp;tr":["udp%3A%2F%2Ftracker.openbittorrent.com%3A80","udp%3A%2F%2Fopen.demonii.com%3A1337","udp%3A%2F%2Ftracker.coppersurfer.tk%3A6969","udp%3A%2F%2Fexodus.desync.com%3A6969"],"infoHash":"8d94321ffcf34ebc9a4bf1d73abd28dcf83696da","infoHashBuffer":{"type":"Buffer","data":[141,148,50,31,252,243,78,188,154,75,241,215,58,189,40,220,248,54,150,218]},"announce":[],"urlList":[]}}