{"title":"IPZ-580 Aino Kishi JAV CENSORED","uid":12022353,"size":1412250316,"categoryP":"porn","categoryS":"movies","magnet":"?xt=urn:btih:98578675a3082443bac71764589331572a56e46f&amp;dn=IPZ-580+Aino+Kishi+JAV+CENSORED&amp;tr=udp%3A%2F%2Ftracker.openbittorrent.com%3A80&amp;tr=udp%3A%2F%2Fopen.demonii.com%3A1337&amp;tr=udp%3A%2F%2Ftracker.coppersurfer.tk%3A6969&amp;tr=udp%3A%2F%2Fexodus.desync.com%3A6969","seeders":1,"leechers":0,"uploader":"3xplanet","files":1,"time":1434465241,"description":"IPZ-580 Aino Kishi JAV CENSORED\nCover &lt;a href=&quot;\nhttp://www.3xplanet.com/view/95736.html&quot; rel=&quot;nofollow&quot; target=&quot;_NEW&quot;&gt;\nhttp://www.3xplanet.com/view/95736.html&lt;/a&gt;\nScreenshot &lt;a href=&quot;\nhttp://www.3xplanet.com/view/95798.html&quot; rel=&quot;nofollow&quot; target=&quot;_NEW&quot;&gt;\nhttp://www.3xplanet.com/view/95798.html&lt;/a&gt;\nTitle: \nStarring: Aino Kishi\nStudio:  Idea pocket\n\nTag: JAV, CENSORED, Idea pocket, slut, slender, drama, Work alone","torrent":{"xt":"urn:btih:98578675a3082443bac71764589331572a56e46f","amp;dn":"IPZ-580+Aino+Kishi+JAV+CENSORED","amp;tr":["udp%3A%2F%2Ftracker.openbittorrent.com%3A80","udp%3A%2F%2Fopen.demonii.com%3A1337","udp%3A%2F%2Ftracker.coppersurfer.tk%3A6969","udp%3A%2F%2Fexodus.desync.com%3A6969"],"infoHash":"98578675a3082443bac71764589331572a56e46f","infoHashBuffer":{"type":"Buffer","data":[152,87,134,117,163,8,36,67,186,199,23,100,88,147,49,87,42,86,228,111]},"announce":[],"urlList":[]}}