{"title":"CumeatingCuckolds - Stella Cox 1080p","uid":14966099,"size":1314722212,"categoryP":"porn","categoryS":"hd___movies","magnet":"?xt=urn:btih:a241a8340165c58829c48f0386204ea2eb827ae8&amp;dn=CumeatingCuckolds+-+Stella+Cox+1080p&amp;tr=udp%3A%2F%2Ftracker.leechers-paradise.org%3A6969&amp;tr=udp%3A%2F%2Fzer0day.ch%3A1337&amp;tr=udp%3A%2F%2Fopen.demonii.com%3A1337&amp;tr=udp%3A%2F%2Ftracker.coppersurfer.tk%3A6969&amp;tr=udp%3A%2F%2Fexodus.desync.com%3A6969","seeders":1,"leechers":0,"uploader":"merzedes","files":1,"time":1466183527,"description":"The Truth \r\n\r\nStella Cox\r\n\r\n\r\n1080p MP4 only.\r\n\r\n\r\nStella Cox is going to have to tell her husband the real truth, and turn him into the cuckold that he is. She is going to have to explain that she needs him to suck cock, and swallow cum. She is going to have the day of her life. Her husband however, is in for something totally new.\r\n\r\nScreens \nhttp://s33.postimg.org/4g1cj59of/cec18junscr.jpg\r\n\r\nUploaded by Merzedes and Shallow2\r\n\r\n21 000 Femdom/BDSM/Fetish torrentuploads since 2004, including almost everything from Kink/Intersect.\r\n\r\nJust keep on leaving us nice comments below and we are happy for the next 20k:)\r\n\r\nAlso, a huge thanks to Kink.com for making the videos we all love (and Intersect and all the others too ofcourse). Keep up the awesome work!!!\r\n\r\nAny Questions ?? Read our FAQ!!\r\n \nhttps://yuq.me/users/23/079/W2kwa6hEeP.png\r\n \nhttps://s16.postimg.org/rxyfmji7p/Merzedes_Shallow2_FAQ_The_Pirate_Bay.jpg\r\n\r\nCheers :-)","torrent":{"xt":"urn:btih:a241a8340165c58829c48f0386204ea2eb827ae8","amp;dn":"CumeatingCuckolds+-+Stella+Cox+1080p","amp;tr":["udp%3A%2F%2Ftracker.leechers-paradise.org%3A6969","udp%3A%2F%2Fzer0day.ch%3A1337","udp%3A%2F%2Fopen.demonii.com%3A1337","udp%3A%2F%2Ftracker.coppersurfer.tk%3A6969","udp%3A%2F%2Fexodus.desync.com%3A6969"],"infoHash":"a241a8340165c58829c48f0386204ea2eb827ae8","infoHashBuffer":{"type":"Buffer","data":[162,65,168,52,1,101,197,136,41,196,143,3,134,32,78,162,235,130,122,232]},"announce":[],"urlList":[]}}