{"title":"Le Le - Partytime [2012]","uid":7117656,"size":43985590,"categoryP":"audio","categoryS":"music","magnet":"?xt=urn:btih:aa7535cf6eda5047eb4a2158ecb97ab5bfc2c294&amp;dn=Le+Le+-+Partytime+%5B2012%5D&amp;tr=udp%3A%2F%2Ftracker.openbittorrent.com%3A80&amp;tr=udp%3A%2F%2Fopen.demonii.com%3A1337&amp;tr=udp%3A%2F%2Ftracker.coppersurfer.tk%3A6969&amp;tr=udp%3A%2F%2Fexodus.desync.com%3A6969","seeders":1,"leechers":1,"uploader":"jasper92","files":14,"time":1332260376,"description":"1.  We Come To Play 1:55 min.\n2.  Normal 3:27 min.\n3.  En Pierre 3:42 min.\n4.  Pearl Necklace 4:05 min.\n5.  Damien 4:09 min.\n6.  Crazy Shaped Lady 2:56 min.\n7.  Drunken Cigarettes 3:47 min.\n8.  Neen 3:29 min.\n9.  Private Guy 3:31 min.\n10. Scary Sweaters 3:25 min.\n11. Sexual Hair 3:43 min.\n12. Komkommers 3:31 min.\n13. Morning Drinks 5:17 min.\n14. Denise 2:49 min.","torrent":{"xt":"urn:btih:aa7535cf6eda5047eb4a2158ecb97ab5bfc2c294","amp;dn":"Le+Le+-+Partytime+%5B2012%5D","amp;tr":["udp%3A%2F%2Ftracker.openbittorrent.com%3A80","udp%3A%2F%2Fopen.demonii.com%3A1337","udp%3A%2F%2Ftracker.coppersurfer.tk%3A6969","udp%3A%2F%2Fexodus.desync.com%3A6969"],"infoHash":"aa7535cf6eda5047eb4a2158ecb97ab5bfc2c294","infoHashBuffer":{"type":"Buffer","data":[170,117,53,207,110,218,80,71,235,74,33,88,236,185,122,181,191,194,194,148]},"announce":[],"urlList":[]}}