{"title":"Less than Jake - Greetins and Salutations From","uid":8014930,"size":33050112,"categoryP":"audio","categoryS":"music","magnet":"?xt=urn:btih:c00f9311abc5679354849f532d79b10946bfba81&amp;dn=Less+than+Jake+-+Greetins+and+Salutations+From&amp;tr=udp%3A%2F%2Ftracker.openbittorrent.com%3A80&amp;tr=udp%3A%2F%2Fopen.demonii.com%3A1337&amp;tr=udp%3A%2F%2Ftracker.coppersurfer.tk%3A6969&amp;tr=udp%3A%2F%2Fexodus.desync.com%3A6969","seeders":1,"leechers":0,"uploader":"rod_tk","files":12,"time":1358087364,"description":"Less Than Jake - Greetings and Salutations From (2013\nGenre: Ska, Punk\n\ntracklist: \n01. The New Auld Lang Syne\n02. Younger Lungs\n03. Goodbye Mr. Personality\n04. A Return to Headphones\n05. Harvey Wallbanger\n06. Flag Holder's Union\n07. Can't Yell Any Louder\n08. View From the Middle\n09. Oldest Trick In the Book\n10. Done and Dusted\n11. Finer Points of Forgiveness\n12. Life Led Out Loud\n","torrent":{"xt":"urn:btih:c00f9311abc5679354849f532d79b10946bfba81","amp;dn":"Less+than+Jake+-+Greetins+and+Salutations+From","amp;tr":["udp%3A%2F%2Ftracker.openbittorrent.com%3A80","udp%3A%2F%2Fopen.demonii.com%3A1337","udp%3A%2F%2Ftracker.coppersurfer.tk%3A6969","udp%3A%2F%2Fexodus.desync.com%3A6969"],"infoHash":"c00f9311abc5679354849f532d79b10946bfba81","infoHashBuffer":{"type":"Buffer","data":[192,15,147,17,171,197,103,147,84,132,159,83,45,121,177,9,70,191,186,129]},"announce":[],"urlList":[]}}