{"title":"Silicon.Valley.S03E10.HDTV.x264-FLEET","uid":15168082,"size":202731135,"categoryP":"video","categoryS":"tv_shows","magnet":"?xt=urn:btih:c1aeb84be6fe3b14bed2d9f114b46d84578b8e1d&amp;dn=Silicon.Valley.S03E10.HDTV.x264-FLEET&amp;tr=udp%3A%2F%2Ftracker.leechers-paradise.org%3A6969&amp;tr=udp%3A%2F%2Fzer0day.ch%3A1337&amp;tr=udp%3A%2F%2Fopen.demonii.com%3A1337&amp;tr=udp%3A%2F%2Ftracker.coppersurfer.tk%3A6969&amp;tr=udp%3A%2F%2Fexodus.desync.com%3A6969","seeders":1,"leechers":0,"uploader":"TvTeam","files":5,"time":1467365882,"description":"https://www.torrenting.com\r\n\r\nSign up is OPEN - for time being. Come and have fun","torrent":{"xt":"urn:btih:c1aeb84be6fe3b14bed2d9f114b46d84578b8e1d","amp;dn":"Silicon.Valley.S03E10.HDTV.x264-FLEET","amp;tr":["udp%3A%2F%2Ftracker.leechers-paradise.org%3A6969","udp%3A%2F%2Fzer0day.ch%3A1337","udp%3A%2F%2Fopen.demonii.com%3A1337","udp%3A%2F%2Ftracker.coppersurfer.tk%3A6969","udp%3A%2F%2Fexodus.desync.com%3A6969"],"infoHash":"c1aeb84be6fe3b14bed2d9f114b46d84578b8e1d","infoHashBuffer":{"type":"Buffer","data":[193,174,184,75,230,254,59,20,190,210,217,241,20,180,109,132,87,139,142,29]},"announce":[],"urlList":[]}}