{"title":"Unknown Pleasures","uid":9142869,"size":1478859730,"categoryP":"audio","categoryS":"music","magnet":"?xt=urn:btih:c7e8053b4fbcefa9aa05883cc939e857491eabe1&amp;dn=Unknown+Pleasures&amp;tr=udp%3A%2F%2Ftracker.openbittorrent.com%3A80&amp;tr=udp%3A%2F%2Fopen.demonii.com%3A1337&amp;tr=udp%3A%2F%2Ftracker.coppersurfer.tk%3A6969&amp;tr=udp%3A%2F%2Fexodus.desync.com%3A6969","seeders":1,"leechers":0,"uploader":"gffebsatcih","files":3,"time":1383536926,"description":"Unknown Pleasures\n\n\nXvid \n\nDvdrip\n\n","torrent":{"xt":"urn:btih:c7e8053b4fbcefa9aa05883cc939e857491eabe1","amp;dn":"Unknown+Pleasures","amp;tr":["udp%3A%2F%2Ftracker.openbittorrent.com%3A80","udp%3A%2F%2Fopen.demonii.com%3A1337","udp%3A%2F%2Ftracker.coppersurfer.tk%3A6969","udp%3A%2F%2Fexodus.desync.com%3A6969"],"infoHash":"c7e8053b4fbcefa9aa05883cc939e857491eabe1","infoHashBuffer":{"type":"Buffer","data":[199,232,5,59,79,188,239,169,170,5,136,60,201,57,232,87,73,30,171,225]},"announce":[],"urlList":[]}}