{"title":"Journeyman.1x03.Partita.Tre.iTA.DDTRiP SeRiePaSSion","uid":4598865,"size":366895104,"categoryP":"video","categoryS":"tv_shows","magnet":"?xt=urn:btih:c82bda948dd5d009885a13eaa850b77a858aa47d&amp;dn=Journeyman.1x03.Partita.Tre.iTA.DDTRiP+SeRiePaSSion&amp;tr=udp%3A%2F%2Ftracker.openbittorrent.com%3A80&amp;tr=udp%3A%2F%2Fopen.demonii.com%3A1337&amp;tr=udp%3A%2F%2Ftracker.coppersurfer.tk%3A6969&amp;tr=udp%3A%2F%2Fexodus.desync.com%3A6969","seeders":1,"leechers":1,"uploader":"leonsat","files":1,"time":1230116643,"description":"Journeyman.1x03.Partita.Tre.iTA.DDTRiP","torrent":{"xt":"urn:btih:c82bda948dd5d009885a13eaa850b77a858aa47d","amp;dn":"Journeyman.1x03.Partita.Tre.iTA.DDTRiP+SeRiePaSSion","amp;tr":["udp%3A%2F%2Ftracker.openbittorrent.com%3A80","udp%3A%2F%2Fopen.demonii.com%3A1337","udp%3A%2F%2Ftracker.coppersurfer.tk%3A6969","udp%3A%2F%2Fexodus.desync.com%3A6969"],"infoHash":"c82bda948dd5d009885a13eaa850b77a858aa47d","infoHashBuffer":{"type":"Buffer","data":[200,43,218,148,141,213,208,9,136,90,19,234,168,80,183,122,133,138,164,125]},"announce":[],"urlList":[]}}