{"title":"National.Geographic.Inside.Americas.Secret.Weapons.HDTV.XviD-W4F","uid":4623699,"size":376776710,"categoryP":"video","categoryS":"tv_shows","magnet":"?xt=urn:btih:cb5e24b83e4cea99dd97e0ee76d712cc6f635ba2&amp;dn=National.Geographic.Inside.Americas.Secret.Weapons.HDTV.XviD-W4F&amp;tr=udp%3A%2F%2Ftracker.openbittorrent.com%3A80&amp;tr=udp%3A%2F%2Fopen.demonii.com%3A1337&amp;tr=udp%3A%2F%2Ftracker.coppersurfer.tk%3A6969&amp;tr=udp%3A%2F%2Fexodus.desync.com%3A6969","seeders":1,"leechers":0,"uploader":"noway25","files":28,"time":1231132829,"description":"[W4F PRESENTS]: National.Geographic.Inside.Americas.Secret.Weapons.HDTV.XviD-W4F [DATE]: 12/06/2008\nDescription: Rare access to a highly classified division of the\nDefense Department reveals the latest generation of defense technologies, including\nunmanned aerial vehicles and hypersonic aircraft\n","torrent":{"xt":"urn:btih:cb5e24b83e4cea99dd97e0ee76d712cc6f635ba2","amp;dn":"National.Geographic.Inside.Americas.Secret.Weapons.HDTV.XviD-W4F","amp;tr":["udp%3A%2F%2Ftracker.openbittorrent.com%3A80","udp%3A%2F%2Fopen.demonii.com%3A1337","udp%3A%2F%2Ftracker.coppersurfer.tk%3A6969","udp%3A%2F%2Fexodus.desync.com%3A6969"],"infoHash":"cb5e24b83e4cea99dd97e0ee76d712cc6f635ba2","infoHashBuffer":{"type":"Buffer","data":[203,94,36,184,62,76,234,153,221,151,224,238,118,215,18,204,111,99,91,162]},"announce":[],"urlList":[]}}