{"title":"PornMegaLoad.15.10.08.Harmony.Reigns.Homemaker.Humpin.XXX.1080p.","uid":12619857,"size":1175274333,"categoryP":"porn","categoryS":"hd___movies","magnet":"?xt=urn:btih:d6a8ad903f3f0e2a86add676d307ae1c3d3b7df3&amp;dn=PornMegaLoad.15.10.08.Harmony.Reigns.Homemaker.Humpin.XXX.1080p.&amp;tr=udp%3A%2F%2Ftracker.leechers-paradise.org%3A6969&amp;tr=udp%3A%2F%2Fzer0day.ch%3A1337&amp;tr=udp%3A%2F%2Fopen.demonii.com%3A1337&amp;tr=udp%3A%2F%2Ftracker.coppersurfer.tk%3A6969&amp;tr=udp%3A%2F%2Fexodus.desync.com%3A6969","seeders":1,"leechers":0,"uploader":"0-DayXXX","files":1,"time":1445580461,"description":"---------------------------------------\nPornMegaLoad.15.10.08.Harmony.Reigns.Homemaker.Humpin.XXX.1080p.MP4-KTR\n---------------------------------------\nScreenshot(s): \nhttp://imgsay.com/?v=478760.jpg\n\n---------------------------------------\nFormat:\t\tMPEG-4\nSize:\t\t1.09 GiB\nDuration:\t19min 19s\nResolution:\t1920x1080\nBitrate:\t8000Kbps\n---------------------------------------\nIf you like this torrent, please post a comment!\n\nDon't forget to seed!","torrent":{"xt":"urn:btih:d6a8ad903f3f0e2a86add676d307ae1c3d3b7df3","amp;dn":"PornMegaLoad.15.10.08.Harmony.Reigns.Homemaker.Humpin.XXX.1080p.","amp;tr":["udp%3A%2F%2Ftracker.leechers-paradise.org%3A6969","udp%3A%2F%2Fzer0day.ch%3A1337","udp%3A%2F%2Fopen.demonii.com%3A1337","udp%3A%2F%2Ftracker.coppersurfer.tk%3A6969","udp%3A%2F%2Fexodus.desync.com%3A6969"],"infoHash":"d6a8ad903f3f0e2a86add676d307ae1c3d3b7df3","infoHashBuffer":{"type":"Buffer","data":[214,168,173,144,63,63,14,42,134,173,214,118,211,7,174,28,61,59,125,243]},"announce":[],"urlList":[]}}