{"title":"Runner's World Magazine - June 2012","uid":7239001,"size":92641669,"categoryP":"other","categoryS":"e_books","magnet":"?xt=urn:btih:db90820970213ad4f1406ecf5d34fc931d2d65b7&amp;dn=Runner%27s+World+Magazine+-+June+2012&amp;tr=udp%3A%2F%2Ftracker.openbittorrent.com%3A80&amp;tr=udp%3A%2F%2Fopen.demonii.com%3A1337&amp;tr=udp%3A%2F%2Ftracker.coppersurfer.tk%3A6969&amp;tr=udp%3A%2F%2Fexodus.desync.com%3A6969","seeders":1,"leechers":0,"uploader":"bpfine","files":5,"time":1336083087,"description":"Runner's World Magazine - June 2012\n\n130 Pages  |  HQ PDF  |  English","torrent":{"xt":"urn:btih:db90820970213ad4f1406ecf5d34fc931d2d65b7","amp;dn":"Runner%27s+World+Magazine+-+June+2012","amp;tr":["udp%3A%2F%2Ftracker.openbittorrent.com%3A80","udp%3A%2F%2Fopen.demonii.com%3A1337","udp%3A%2F%2Ftracker.coppersurfer.tk%3A6969","udp%3A%2F%2Fexodus.desync.com%3A6969"],"infoHash":"db90820970213ad4f1406ecf5d34fc931d2d65b7","infoHashBuffer":{"type":"Buffer","data":[219,144,130,9,112,33,58,212,241,64,110,207,93,52,252,147,29,45,101,183]},"announce":[],"urlList":[]}}