{"title":"Neal Boortz - Thursday, November 10, 2011 MP3 not CF","uid":6808920,"size":44173780,"categoryP":"audio","categoryS":"other","magnet":"?xt=urn:btih:fe2676329b8c5cda49b1942cda0f011dd22f63c1&amp;dn=Neal+Boortz+-+Thursday%2C+November+10%2C+2011+MP3+not+CF&amp;tr=udp%3A%2F%2Ftracker.openbittorrent.com%3A80&amp;tr=udp%3A%2F%2Fopen.demonii.com%3A1337&amp;tr=udp%3A%2F%2Ftracker.coppersurfer.tk%3A6969&amp;tr=udp%3A%2F%2Fexodus.desync.com%3A6969","seeders":1,"leechers":0,"uploader":"amuck5","files":4,"time":1320970506,"description":"Neal Boortz - Thursday, November 10, 2011 MP3 not CF\n\nAlternate: fenopy.eu slash user slash amuck5","torrent":{"xt":"urn:btih:fe2676329b8c5cda49b1942cda0f011dd22f63c1","amp;dn":"Neal+Boortz+-+Thursday%2C+November+10%2C+2011+MP3+not+CF","amp;tr":["udp%3A%2F%2Ftracker.openbittorrent.com%3A80","udp%3A%2F%2Fopen.demonii.com%3A1337","udp%3A%2F%2Ftracker.coppersurfer.tk%3A6969","udp%3A%2F%2Fexodus.desync.com%3A6969"],"infoHash":"fe2676329b8c5cda49b1942cda0f011dd22f63c1","infoHashBuffer":{"type":"Buffer","data":[254,38,118,50,155,140,92,218,73,177,148,44,218,15,1,29,210,47,99,193]},"announce":[],"urlList":[]}}